RecoEvalTest/__init__.py
RecoEvalTest/add.py
RecoEvalTest/analysis.py
RecoEvalTest/subtract.py
RecoEvalTest/extras/__init__.py
RecoEvalTest/extras/divide.py
RecoEvalTest/extras/multiply.py
RecoEvalTest-0.0.7.dist-info/METADATA
RecoEvalTest-0.0.7.dist-info/WHEEL
RecoEvalTest-0.0.7.dist-info/top_level.txt
RecoEvalTest-0.0.7.dist-info/RECORD
