Metadata-Version: 2.1
Name: RecoEvalTest
Version: 0.0.7
Summary: My first Python package
Author: Minglei Guo
Author-email: <mingleiguo@microsoft.com>
Keywords: python,first package
Classifier: Development Status :: 3 - Alpha
Classifier: Intended Audience :: Education
Classifier: Programming Language :: Python :: 2
Classifier: Programming Language :: Python :: 3
Classifier: Operating System :: MacOS :: MacOS X
Classifier: Operating System :: Microsoft :: Windows
Requires-Dist: pandas
Requires-Dist: RecoEvalTest
Requires-Dist: recoevaltest
